cookiefarm/__init__.py
cookiefarm/cli.py
cookiefarm/exploit_config.py
cookiefarm/exploit_executor.py
cookiefarm/exploiter_manager.py
cookiefarm/flagids_handler.py
cookiefarm/logger.py
cookiefarm/server_config.py
cookiefarm/test_executor.py
cookiefarm/bin/arm64/darwin/ckc
cookiefarm/bin/arm64/linux/ckc
cookiefarm/bin/arm64/windows/ckc.exe
cookiefarm/bin/x86_64/darwin/ckc
cookiefarm/bin/x86_64/linux/ckc
cookiefarm/bin/x86_64/windows/ckc.exe
cookiefarm-1.2.9.dist-info/METADATA
cookiefarm-1.2.9.dist-info/WHEEL
cookiefarm-1.2.9.dist-info/entry_points.txt
cookiefarm-1.2.9.dist-info/licenses/LICENSE
cookiefarm-1.2.9.dist-info/RECORD
