Metadata-Version: 2.4
Name: cookiefarm
Version: 1.2.9
Summary: Python decorator for parallel exploit dispatch in Attack & Defense CTFs using the CookieFarm framework.
Project-URL: Homepage, https://github.com/ByteTheCookies/CookieFarmExploiter
Author-email: ByteTheCookies <bytethecookies@proton.me>
License: MIT License
License-File: LICENSE
Classifier: License :: OSI Approved :: MIT License
Classifier: Programming Language :: Python :: 3
Requires-Python: >=3.12
Requires-Dist: requests
